[
      {
        "username": "Miss Joanna O'Keefe",
        "email": "Johann_Ruecker@hotmail.com",
        "password": "YW05Y7XJmjW9nGl"
      },
      {
        "username": "Stella Fay",
        "email": "Jazmin_Boyer@yahoo.com",
        "password": "5CnxOjjC0yeKkgG"
      },
      {
        "username": "Dale Stamm PhD",
        "email": "Brenna.Champlin56@hotmail.com",
        "password": "Wu5vEOnxSk20Pio"
      },
      {
        "username": "Bradley Trantow",
        "email": "Rahul10@hotmail.com",
        "password": "mYWsPtfb8_SBYl4"
      },
      {
        "username": "Rosie Walsh",
        "email": "Myrl.Tromp23@gmail.com",
        "password": "R5QW9G5gE0PCeLL"
      }
    ]